<?xml version="1.0" encoding="ISO-8859-1"?>
<AUTOCOMPLETE>
	<AJAX>
		<serviceUrl>autocompleteAjax</serviceUrl>
		<minChars>2</minChars>
		<onSelect type="js">
			<![CDATA[function(data){;}]]>
		</onSelect>
		<!--<maxHeight>400</maxHeight>
		<width>300</width>
		<zIndex>9999</zIndex>-->
		<deferRequestBy>1000</deferRequestBy>
        <selectOnSingleResult>false</selectOnSingleResult>
		<datasource>PS</datasource>
		<storedQuery>AUTOCOMPLETE.AC_ASL</storedQuery>
		<maxResults>40</maxResults>
	</AJAX> 
	<LIST>
	    <title>ASL Assistenza</title>
	    <id_wk>WK_SCHEDA_ANAGRAFICA_AC_ASL</id_wk>
	    <onSelect type="js">
            <![CDATA[function(data){}]]>
		</onSelect>
	</LIST>
	<QUERY_BINDS>
        <reg_codice>0</reg_codice>
    </QUERY_BINDS>
</AUTOCOMPLETE>	 
    